CycleQueue/AgentCycle.py
CycleQueue/AgentCycleQueueMessager.py
CycleQueue/AgentManagerCycle.py
CycleQueue/MailerCycleQueueMessager.py
CycleQueue/Message.py
CycleQueue/MessageMailerCycle.py
CycleQueue/ProcessThread.py
CycleQueue/Result.py
CycleQueue/ResultCycle.py
CycleQueue/ResultDPOP.py
CycleQueue/__init__.py
DCOPGenetor/DCOPGenetor.py
DCOPGenetor/GUIGenetor.py
DCOPGenetor/GeneateRandomGraph.py
DCOPGenetor/__init__.py
DCOPGenetor/prettyXml.py
DCOPPharse/DFSgeneration.py
DCOPPharse/DFSview.py
DCOPPharse/MostConnectedHeuristic.py
DCOPPharse/ParserGeneral.py
DCOPPharse/PriorityGeneration.py
DCOPPharse/PriorityView.py
DCOPPharse/Problem.py
DCOPPharse/ProblemParse.py
DCOPPharse/ScoringHeuristic.py
DCOPPharse/TreeGenerator.py
DCOPPharse/__init__.py
DSA/DsaA_Agent.py
DSA/__init__.py
Solve/Solver.py
Solve/__init__.py
dcop_platform-1.0.0.dist-info/METADATA
dcop_platform-1.0.0.dist-info/WHEEL
dcop_platform-1.0.0.dist-info/top_level.txt
dcop_platform-1.0.0.dist-info/RECORD
